{
    "last_updated": "2026-05-18 20:52:29",
    "execution_id": 1779151949.6293607,
    "projections": {
        "TSLA": {
            "expected_value": 192.64,
            "ci_low": 103.26,
            "ci_high": 345.11,
            "sentiment_score": 0.0,
            "headline": "SpaceX eyes 5-for-1 stock split as IPO takes shape",
            "volatility_alert": false
        },
        "F": {
            "expected_value": 14.07,
            "ci_low": 7.34,
            "ci_high": 24.46,
            "sentiment_score": 0.7,
            "headline": "Ford Details European Growth Strategy, Signs EDF Energy-Storage Agreement",
            "volatility_alert": false
        },
        "XOM": {
            "expected_value": 134.88,
            "ci_low": 74.28,
            "ci_high": 233.48,
            "sentiment_score": 0.599,
            "headline": "Exxon Mobil (XOM) Valuation Check As Legal Win And Strong Q1 Meet Rising Crude Prices",
            "volatility_alert": false
        },
        "PFE": {
            "expected_value": 31.2,
            "ci_low": 16.98,
            "ci_high": 52.13,
            "sentiment_score": 0.0,
            "headline": "3 Deeply Undervalued Stocks You Can Buy for Less Than $100 Right Now",
            "volatility_alert": false
        },
        "CL=F": {
            "expected_value": 90.01,
            "ci_low": 48.02,
            "ci_high": 157.01,
            "sentiment_score": 0.0,
            "headline": "US\u2013Iran stalemate: A look at year-end oil price predictions",
            "volatility_alert": false
        }
    }
}