{
    "last_updated": "2026-05-17 13:53:19",
    "execution_id": 1779040399.8772988,
    "projections": {
        "TSLA": {
            "expected_value": 191.83,
            "ci_low": 104.29,
            "ci_high": 321.91,
            "sentiment_score": 0.0,
            "headline": "Bank of America resets Google stock forecast before key event",
            "volatility_alert": false
        },
        "F": {
            "expected_value": 14.01,
            "ci_low": 7.41,
            "ci_high": 24.04,
            "sentiment_score": 0.459,
            "headline": "How much is Ford Energy worth? RBC breaks down the valuation",
            "volatility_alert": false
        },
        "XOM": {
            "expected_value": 133.19,
            "ci_low": 68.18,
            "ci_high": 230.06,
            "sentiment_score": 0.71,
            "headline": "1 Brilliant Energy Stock to Buy Now and Hold for the Long Term",
            "volatility_alert": false
        },
        "PFE": {
            "expected_value": 30.89,
            "ci_low": 16.52,
            "ci_high": 51.46,
            "sentiment_score": -0.34,
            "headline": "Up 231%, Is RTX Proving Why It Was a Mistake for Honeywell to Replace RTX in the Dow Jones Industrial Average?",
            "volatility_alert": false
        },
        "CL=F": {
            "expected_value": 91.94,
            "ci_low": 49.21,
            "ci_high": 156.68,
            "sentiment_score": 0.202,
            "headline": "Dow Jones Futures Due With Treasury Yields, Oil Prices In Focus; Nvidia Earnings Ahead",
            "volatility_alert": false
        }
    }
}