{
    "last_updated": "2026-05-14 18:49:39",
    "execution_id": 1778798979.9291923,
    "projections": {
        "TSLA": {
            "expected_value": 203.55,
            "ci_low": 108.23,
            "ci_high": 366.47,
            "sentiment_score": 0.65,
            "headline": "Record deliveries reported. Cybertruck margins expanding.",
            "volatility_alert": false
        },
        "F": {
            "expected_value": 13.85,
            "ci_low": 7.45,
            "ci_high": 23.34,
            "sentiment_score": 0.2,
            "headline": "EV transition costs balanced by strong legacy fleet sales.",
            "volatility_alert": false
        },
        "XOM": {
            "expected_value": 133.94,
            "ci_low": 74.71,
            "ci_high": 224.79,
            "sentiment_score": 0.55,
            "headline": "Upstream production exceeding targets. Favorable crack spreads.",
            "volatility_alert": false
        },
        "PFE": {
            "expected_value": 31.65,
            "ci_low": 17.16,
            "ci_high": 53.26,
            "sentiment_score": 0.1,
            "headline": "Pipeline progression steady. Cost-realignment phase active.",
            "volatility_alert": false
        },
        "CL=F": {
            "expected_value": 93.18,
            "ci_low": 49.25,
            "ci_high": 161.72,
            "sentiment_score": 0.4,
            "headline": "Geopolitical risk premium priced into near-term contracts.",
            "volatility_alert": false
        }
    }
}