{
    "last_updated": "2026-05-18 07:47:55",
    "execution_id": 1779104875.9118922,
    "projections": {
        "TSLA": {
            "expected_value": 195.26,
            "ci_low": 103.98,
            "ci_high": 331.9,
            "sentiment_score": 0.296,
            "headline": "Tesla Stock Drops as CFO Sells Shares. Can It Hold Above $400?",
            "volatility_alert": false
        },
        "F": {
            "expected_value": 13.5,
            "ci_low": 7.08,
            "ci_high": 24.13,
            "sentiment_score": 0.0,
            "headline": "Ford to build Bronco SUV in Spain as part of European revival plan",
            "volatility_alert": false
        },
        "XOM": {
            "expected_value": 135.24,
            "ci_low": 71.09,
            "ci_high": 227.04,
            "sentiment_score": 0.691,
            "headline": "Sintana Energy raises $11.5m to support exploration plans in Namibia",
            "volatility_alert": false
        },
        "PFE": {
            "expected_value": 30.98,
            "ci_low": 16.09,
            "ci_high": 54.51,
            "sentiment_score": -0.34,
            "headline": "Up 231%, Is RTX Proving Why It Was a Mistake for Honeywell to Replace RTX in the Dow Jones Industrial Average?",
            "volatility_alert": false
        },
        "CL=F": {
            "expected_value": 90.18,
            "ci_low": 47.96,
            "ci_high": 150.92,
            "sentiment_score": -0.296,
            "headline": "Bitcoin and ethereum prices today, Monday, May 18, 2026: Prices are down and moving lower this morning",
            "volatility_alert": false
        }
    }
}