{
    "last_updated": "2026-05-13 19:19:12",
    "execution_id": 1778714352.0386162,
    "projections": {
        "TSLA": {
            "expected_value": 202.56,
            "ci_low": 105.92,
            "ci_high": 330.31,
            "sentiment_score": 0.65,
            "volatility_alert": false
        },
        "F": {
            "expected_value": 13.53,
            "ci_low": 7.27,
            "ci_high": 23.1,
            "sentiment_score": 0.2,
            "volatility_alert": false
        },
        "XOM": {
            "expected_value": 134.31,
            "ci_low": 69.11,
            "ci_high": 233.0,
            "sentiment_score": 0.55,
            "volatility_alert": false
        },
        "PFE": {
            "expected_value": 31.22,
            "ci_low": 16.78,
            "ci_high": 50.78,
            "sentiment_score": 0.1,
            "volatility_alert": false
        },
        "CL=F": {
            "expected_value": 91.6,
            "ci_low": 47.56,
            "ci_high": 152.42,
            "sentiment_score": 0.4,
            "volatility_alert": false
        }
    }
}